bbplot/__init__.py
bbplot/bijan.py
bbplot-0.0.2.dist-info/LICENSE
bbplot-0.0.2.dist-info/METADATA
bbplot-0.0.2.dist-info/WHEEL
bbplot-0.0.2.dist-info/top_level.txt
bbplot-0.0.2.dist-info/RECORD
